sawa/__init__.py
sawa/__version__.py
sawa/cli.py
sawa/include.py
sawa/main.py
sawa/process.py
sawa/util.py
sawa/enum/__init__.py
sawa/enum/effected.py
sawa/enum/file_error.py
sawa/enum/token_error.py
sawa-1.0.4.dist-info/LICENSE.md
sawa-1.0.4.dist-info/METADATA
sawa-1.0.4.dist-info/WHEEL
sawa-1.0.4.dist-info/entry_points.txt
sawa-1.0.4.dist-info/top_level.txt
sawa-1.0.4.dist-info/RECORD
