Metadata-Version: 2.1
Name: sawa
Version: 1.0.4
Summary: an open source programming language, an interpreter to be precise, where you can write Python code using Javanese character.
Home-page: https://github.com/lantip/sawa
Author: Lantip
Author-email: lantip@underpaidworkers.org
License: MIT
Platform: UNKNOWN
Classifier: License :: OSI Approved :: MIT License
Classifier: Programming Language :: Python
Classifier: Programming Language :: Python :: 3
Classifier: Programming Language :: Python :: 3.6
Classifier: Programming Language :: Python :: 3.7
Classifier: Programming Language :: Python :: 3.8
Classifier: Programming Language :: Python :: Implementation :: CPython
Requires-Python: >=3.6.0
